[
  {
    "title": "Some on-air claims about Dominion Voting Systems were false, Fox News acknowledges in statement after deal is announced",
    "link": "https://www.cnn.com/business/live-news/fox-news-dominion-trial-04-18-23/index.html",
    "pubDate": "Wed, 19 Apr 2023 12:44:51 GMT",
    "source": "cnn"
  },
  {
    "title": "Dominion still has pending lawsuits against election deniers such as Rudy Giuliani and Sidney Powell",
    "link": "https://www.cnn.com/business/live-news/fox-news-dominion-trial-04-18-23/h_8d51e3ae2714edaa0dace837305d03b8",
    "pubDate": "",
    "source": "cnn"
  },
  {
    "title": "Here are the 20 specific Fox broadcasts and tweets Dominion says were defamatory",
    "link": "https://www.cnn.com/2023/04/17/media/dominion-fox-news-allegations/index.html",
    "pubDate": "Mon, 17 Apr 2023 16:01:11 GMT",
    "source": "cnn"
  },
  {
    "title": "Judge in Fox News-Dominion defamation trial: 'The parties have resolved their case'",
    "link": "https://www.cnn.com/2023/04/18/media/fox-dominion-settlement/index.html",
    "pubDate": "Wed, 19 Apr 2023 08:28:17 GMT",
    "source": "cnn"
  },
  {
    "title": "'Difficult to say with a straight face': Tapper reacts to Fox News' statement on settlement",
    "link": "https://www.cnn.com/videos/politics/2023/04/18/jake-tapper-dominion-lawsuit-settlement-fox-news-statement-lead-vpx.cnn",
    "pubDate": "Tue, 18 Apr 2023 21:17:44 GMT",
    "source": "cnn"
  },
  {
    "title": "Millions in the US could face massive consequences unless McCarthy can navigate out of a debt trap he set for Biden",
    "link": "https://www.cnn.com/2023/04/18/politics/mccarthy-biden-debt-ceiling/index.html",
    "pubDate": "Tue, 18 Apr 2023 20:34:45 GMT",
    "source": "cnn"
  },
  {
    "title": "White homeowner accused of shooting a Black teen who rang his doorbell turns himself in to face criminal charges",
    "link": "https://www.cnn.com/2023/04/18/us/kansas-city-ralph-yarl-shooting-tuesday/index.html",
    "pubDate": "Wed, 19 Apr 2023 04:29:05 GMT",
    "source": "cnn"
  },
  {
    "title": "Newly released video shows scene of Jeremy Renner's snowplow accident",
    "link": "https://www.cnn.com/videos/us/2023/04/18/jeremy-renner-snowplow-accident-bodycam-nc-melas-contd-vpx.cnn",
    "pubDate": "Tue, 18 Apr 2023 14:09:43 GMT",
    "source": "cnn"
  },
  {
    "title": "Jake Gyllenhaal and Jamie Lee Curtis spent the Covid-19 lockdown together",
    "link": "https://www.cnn.com/2023/04/18/entertainment/jake-gyllenhaal-jamie-lee-curtis-pandemic-living/index.html",
    "pubDate": "Tue, 18 Apr 2023 14:40:32 GMT",
    "source": "cnn"
  },
  {
    "title": "Toddler crawls through White House fence, prompts Secret Service response",
    "link": "https://www.cnn.com/2023/04/18/politics/white-house-toddler/index.html",
    "pubDate": "Tue, 18 Apr 2023 17:38:16 GMT",
    "source": "cnn"
  },
  {
    "title": "Jamie Foxx remains hospitalized nearly a week after 'medical complication'",
    "link": "https://www.cnn.com/2023/04/17/entertainment/jamie-foxx-remains-hospitalized/index.html",
    "pubDate": "Tue, 18 Apr 2023 00:27:07 GMT",
    "source": "cnn"
  },
  {
    "title": "A 13-year-old dies after participating in a Benadryl TikTok 'challenge'",
    "link": "https://www.cnn.com/2023/04/18/us/benadryl-tiktok-challenge-teen-death-wellness/index.html",
    "pubDate": "Wed, 19 Apr 2023 15:01:06 GMT",
    "source": "cnn"
  },
  {
    "title": "See pizza delivery guy take out suspect fleeing police",
    "link": "https://www.cnn.com/videos/us/2023/04/18/pizza-guy-trips-perp-moos-cprog-orig-bdk.cnn",
    "pubDate": "Tue, 18 Apr 2023 16:40:22 GMT",
    "source": "cnn"
  },
  {
    "title": "Netflix is winding down its DVD business after 25 years",
    "link": "https://www.cnn.com/2023/04/18/media/netflix-dvd-red-envelopes/index.html",
    "pubDate": "Tue, 18 Apr 2023 20:10:51 GMT",
    "source": "cnn"
  },
  {
    "title": "FTC chair Lina Khan warns AI could 'turbocharge' fraud and scams",
    "link": "https://www.cnn.com/2023/04/18/tech/lina-khan-ai-warning/index.html",
    "pubDate": "Tue, 18 Apr 2023 17:59:38 GMT",
    "source": "cnn"
  },
  {
    "title": "Eating too much of these foods is driving the rise in type 2 diabetes, study says",
    "link": "https://www.cnn.com/2023/04/17/health/rise-type-2-diabetes-global-wellness/index.html",
    "pubDate": "Mon, 17 Apr 2023 16:02:46 GMT",
    "source": "cnn"
  },
  {
    "title": "ADHD medication abuse in schools is a 'wake-up call'",
    "link": "https://www.cnn.com/2023/04/18/health/teen-misuse-adhd-meds-wellness/index.html",
    "pubDate": "Tue, 25 Apr 2023 17:44:36 GMT",
    "source": "cnn"
  },
  {
    "title": "Apple CEO was presented with an original Macintosh. See his reaction",
    "link": "https://www.cnn.com/videos/tech/2023/04/18/apple-store-mumbai-india-ceo-tim-cook-vedika-sud-ovn-biz-ldn-vpx.cnn",
    "pubDate": "Tue, 18 Apr 2023 09:17:25 GMT",
    "source": "cnn"
  },
  {
    "title": "Democrats bash Justice Clarence Thomas but their plan to investigate ethics allegations is unclear",
    "link": "https://www.cnn.com/2023/04/18/politics/clarence-thomas-ethics-democrats/index.html",
    "pubDate": "Tue, 18 Apr 2023 20:29:46 GMT",
    "source": "cnn"
  },
  {
    "title": "Russia is 'going backwards' in equipment and deploying post WWII-era tanks, according to Western officials",
    "link": "https://www.cnn.com/europe/live-news/russia-ukraine-war-news-04-18-23/index.html",
    "pubDate": "",
    "source": "cnn"
  },
  {
    "title": "Two Russians claiming to be former Wagner commanders admit killing children and civilians in Ukraine",
    "link": "https://www.cnn.com/2023/04/17/europe/wagner-commanders-russia-kill-children-intl-hnk/index.html",
    "pubDate": "Tue, 18 Apr 2023 19:07:52 GMT",
    "source": "cnn"
  },
  {
    "title": "'My stomach is hurting from laughing': Hear panelist's reaction to DeSantis' threat to Disney",
    "link": "https://www.cnn.com/videos/business/2023/04/18/desantis-disney-competition-panel-reax-pt-vpx.cnn",
    "pubDate": "Tue, 18 Apr 2023 03:24:56 GMT",
    "source": "cnn"
  },
  {
    "title": "GOP prepared to block vote to replace Feinstein on Senate Judiciary",
    "link": "https://www.cnn.com/2023/04/18/politics/schumer-senate-feinstein-vote-cardin/index.html",
    "pubDate": "Tue, 18 Apr 2023 22:03:13 GMT",
    "source": "cnn"
  },
  {
    "title": "Oklahoma governor calls on officials to resign over recording of racist and threatening remarks",
    "link": "https://www.cnn.com/2023/04/18/us/mccurtain-county-oklahoma-officials-recording/index.html",
    "pubDate": "Tue, 18 Apr 2023 17:33:17 GMT",
    "source": "cnn"
  },
  {
    "title": "McCarthy slams Biden in handling of US debt ",
    "link": "https://www.cnn.com/videos/politics/2023/04/18/kevin-mccarthy-wall-street-speech-debt-ceiling-biden-economy-vpx.cnn",
    "pubDate": "Tue, 18 Apr 2023 22:03:01 GMT",
    "source": "cnn"
  },
  {
    "title": "US warns Russia not to touch American nuclear technology at Ukrainian nuclear plant",
    "link": "https://www.cnn.com/2023/04/18/politics/us-warns-russia-zaporizhzhia-nuclear-plant/index.html",
    "pubDate": "Wed, 19 Apr 2023 08:35:33 GMT",
    "source": "cnn"
  },
  {
    "title": "Repeated gunshots fired on live TV as ex-lawmaker shot by assassins",
    "link": "https://www.cnn.com/videos/world/2023/04/18/india-ex-lawmaker-atiq-ahmed-assassination-sud-pkg-contd-ovn-intl-hnk-vpx.cnn",
    "pubDate": "Tue, 18 Apr 2023 09:41:42 GMT",
    "source": "cnn"
  },
  {
    "title": "FDA clears the way for additional bivalent boosters for certain vulnerable individuals",
    "link": "https://www.cnn.com/2023/04/18/health/fda-bivalent-booster-additional-doses/index.html",
    "pubDate": "Tue, 18 Apr 2023 15:09:15 GMT",
    "source": "cnn"
  },
  {
    "title": "Maine authorities detained a person of interest after 4 people were found dead in a home and 3 others shot while driving",
    "link": "https://www.cnn.com/2023/04/18/us/maine-shooting-bowdoin-yarmouth/index.html",
    "pubDate": "Wed, 19 Apr 2023 01:49:51 GMT",
    "source": "cnn"
  },
  {
    "title": "Southwest says flights resumed after delays caused by 'tech issues'",
    "link": "https://www.cnn.com/travel/article/southwest-airlines-flight-delays/index.html",
    "pubDate": "Tue, 18 Apr 2023 17:15:29 GMT",
    "source": "cnn"
  },
  {
    "title": "Damar Hamlin cleared to resume football activities after January cardiac arrest",
    "link": "https://www.cnn.com/2023/04/18/sport/damar-hamlin-cleared-to-train-nfl-spt-intl/index.html",
    "pubDate": "Tue, 18 Apr 2023 22:11:37 GMT",
    "source": "cnn"
  },
  {
    "title": "Pilot makes history after landing on top of a 56-story hotel",
    "link": "https://www.cnn.com/videos/travel/2023/03/17/pilot-lands-on-dubai-helipad-cprog-orig-aw-ao.cnn",
    "pubDate": "Sun, 19 Mar 2023 11:22:30 GMT",
    "source": "cnn"
  },
  {
    "title": "Top US Navy admiral defends non-binary sailor amid some Republican criticism",
    "link": "https://www.cnn.com/2023/04/18/politics/gilday-defends-non-binary-sailor/index.html",
    "pubDate": "Tue, 18 Apr 2023 19:56:40 GMT",
    "source": "cnn"
  },
  {
    "title": "Fulton County DA says fake Trump electors are incriminating one another and wants lawyer disqualified ",
    "link": "https://www.cnn.com/2023/04/18/politics/fulton-county-trump-fake-electors/index.html",
    "pubDate": "Wed, 19 Apr 2023 15:31:24 GMT",
    "source": "cnn"
  },
  {
    "title": "High speed trains are racing across the world. But not in America",
    "link": "https://www.cnn.com/travel/article/high-speed-rail-us/index.html",
    "pubDate": "Wed, 19 Apr 2023 02:39:40 GMT",
    "source": "cnn"
  },
  {
    "title": "Podcast: One country musician is calling for other artists to oppose assault rifles",
    "link": "https://www.cnn.com/audio/podcasts/the-assignment/episodes/42a2f0e2-066a-4675-82ff-afe2016a0bb5",
    "pubDate": "",
    "source": "cnn"
  },
  {
    "title": "Here's what you need to know if you haven't filed your return yet — and even if you have",
    "link": "https://www.cnn.com/2023/04/18/success/tax-day-2023-file-irs/index.html",
    "pubDate": "Tue, 18 Apr 2023 14:15:43 GMT",
    "source": "cnn"
  },
  {
    "title": "Undocumented immigrants are paying their taxes today, too",
    "link": "https://www.cnn.com/2023/04/18/us/undocumented-immigrants-taxes-cec/index.html",
    "pubDate": "Tue, 18 Apr 2023 18:29:24 GMT",
    "source": "cnn"
  },
  {
    "title": "Opinion: Why millionaires like us want to pay more in taxes",
    "link": "https://www.cnn.com/2023/04/17/opinions/us-tax-system-wealthy-disney-pearl/index.html",
    "pubDate": "Mon, 17 Apr 2023 19:32:49 GMT",
    "source": "cnn"
  },
  {
    "title": "'World's longest' purpose-built cycling tunnel opens in Norway",
    "link": "https://www.cnn.com/travel/article/worlds-longest-cycling-tunnel/index.html",
    "pubDate": "Tue, 18 Apr 2023 10:44:27 GMT",
    "source": "cnn"
  },
  {
    "title": "Artist rejects photo prize after AI-generated image wins award",
    "link": "https://www.cnn.com/style/article/ai-photo-win-sony-scli-intl/index.html",
    "pubDate": "Tue, 18 Apr 2023 15:27:54 GMT",
    "source": "cnn"
  },
  {
    "title": "These ships disappeared in Lake Superior a century ago. Watch as they're found again",
    "link": "https://www.cnn.com/videos/travel/2023/04/18/century-old-shipwrecks-lake-superior-discovery-contd-orig-zt.cnn",
    "pubDate": "Tue, 18 Apr 2023 19:29:01 GMT",
    "source": "cnn"
  },
  {
    "title": "Erotic images of seniors show sex and intimacy in new light",
    "link": "https://www.cnn.com/style/article/marilyn-minter-artist-elder-sex/index.html",
    "pubDate": "Tue, 18 Apr 2023 03:24:57 GMT",
    "source": "cnn"
  },
  {
    "title": "China's economy is off to a solid start, rising 4.5% in Q1 2023 ",
    "link": "https://www.cnn.com/2023/04/17/economy/china-gdp-q1-2023-intl-hnk/index.html",
    "pubDate": "Tue, 18 Apr 2023 07:01:12 GMT",
    "source": "cnn"
  },
  {
    "title": "Even when wives make as much as husbands, they still do more at home",
    "link": "https://www.cnn.com/2023/04/16/success/husbands-wives-earning-division-of-labor-pew-survey/index.html",
    "pubDate": "Sun, 16 Apr 2023 17:29:49 GMT",
    "source": "cnn"
  },
  {
    "title": "McDonald's is upgrading its burgers",
    "link": "https://www.cnn.com/2023/04/17/business/mcdonalds-burgers/index.html",
    "pubDate": "Mon, 17 Apr 2023 16:31:30 GMT",
    "source": "cnn"
  },
  {
    "title": "Google-parent stock drops on fears it could lose search market share to AI-powered rivals",
    "link": "https://www.cnn.com/2023/04/17/tech/google-ai-search-engine-stock-drop/index.html",
    "pubDate": "Mon, 17 Apr 2023 15:52:19 GMT",
    "source": "cnn"
  },
  {
    "title": "Bidets save you money and reduce waste — we tested the best options out there",
    "link": "https://www.cnn.com/cnn-underscored/reviews/best-bidets?iid=CNNUnderscoredHPcontainer",
    "pubDate": "",
    "source": "cnn"
  },
  {
    "title": "50+ products to make your life easier and our planet cleaner",
    "link": "https://www.cnn.com/cnn-underscored/home/editors-favorite-sustainable-products?iid=CNNUnderscoredHPcontainer",
    "pubDate": "",
    "source": "cnn"
  },
  {
    "title": "Mother's Day is around the corner. Here are 50+ thoughtful gifts she'll love",
    "link": "https://www.cnn.com/cnn-underscored/gifts/best-mothers-day-gifts-2023?iid=CNNUnderscoredHPcontainer",
    "pubDate": "",
    "source": "cnn"
  },
  {
    "title": "A head-to-toe guide of how men should dress this spring, and where they should shop",
    "link": "https://www.cnn.com/cnn-underscored/fashion/mens-spring-fashion-style-guide?iid=CNNUnderscoredHPcontainer",
    "pubDate": "",
    "source": "cnn"
  },
  {
    "title": "42 of the most useful travel products you can buy on Amazon",
    "link": "https://www.cnn.com/cnn-underscored/travel/amazon-travel-products?iid=CNNUnderscoredHPcontainer",
    "pubDate": "",
    "source": "cnn"
  },
  {
    "title": "The 7 best high-yield savings accounts of April 2023",
    "link": "https://www.cnn.com/cnn-underscored/money/high-yield-savings-accounts?iid=CNNUnderscoredHPcontainer",
    "pubDate": "",
    "source": "cnn"
  },
  {
    "title": "Taxes are due tomorrow. Here's how to file for an extension",
    "link": "https://www.cnn.com/cnn-underscored/money/how-to-file-taxes?iid=CNNUnderscoredHPcontainer",
    "pubDate": "",
    "source": "cnn"
  },
  {
    "title": "Composting is an easy way to reduce food waste. Here's how to do it",
    "link": "https://www.cnn.com/cnn-underscored/home/how-to-compost-at-home?iid=CNNUnderscoredHPcontainer",
    "pubDate": "",
    "source": "cnn"
  },
  {
    "title": "We stopped using aluminum foil for cooking and you should too. Here's what to use instead",
    "link": "https://www.cnn.com/cnn-underscored/reviews/mmmat-silicone-mats?iid=CNNUnderscoredHPcontainer",
    "pubDate": "",
    "source": "cnn"
  },
  {
    "title": "The beloved Dyson Supersonic hair dryer is at its lowest price ever",
    "link": "https://www.cnn.com/cnn-underscored/deals/dyson-supersonic-sale-2023-04-17?iid=CNNUnderscoredHPcontainer?iid=CNNUnderscoredHPcontainer",
    "pubDate": "",
    "source": "cnn"
  },
  {
    "title": "Everything you need to know about Way Day 2023, Wayfair's biggest sale of the year",
    "link": "https://www.cnn.com/cnn-underscored/deals/wayfair-way-day-2023-04-17?iid=CNNUnderscoredHPcontainer",
    "pubDate": "",
    "source": "cnn"
  },
  {
    "title": "The 10 best Amazon deals to shop this week",
    "link": "https://www.cnn.com/cnn-underscored/deals/best-amazon-deals-2023-04-12?iid=CNNUnderscoredHPcontainer",
    "pubDate": "",
    "source": "cnn"
  },
  {
    "title": "Mifepristone saved my life ",
    "link": "https://www.cnn.com/2023/04/18/opinions/medication-abortion-mifepristone-miscarriage-jones-ctpr/index.html",
    "pubDate": "Tue, 18 Apr 2023 11:30:00 GMT",
    "source": "cnn"
  },
  {
    "title": "The 2024 presidential alternative many voters will want",
    "link": "https://www.cnn.com/2023/04/18/opinions/2024-presidential-election-alternative-voters-lieberman",
    "pubDate": "",
    "source": "cnn"
  },
  {
    "title": "Why isn't the House Judiciary Committee looking into Thomas?",
    "link": "https://www.cnn.com/2023/04/17/opinions/jim-jordan-clarence-thomas-judiciary-committee-obeidallah/index.html",
    "pubDate": "Mon, 17 Apr 2023 11:37:37 GMT",
    "source": "cnn"
  },
  {
    "title": "Top secrets come spilling out",
    "link": "https://www.cnn.com/2023/04/16/opinions/top-secrets-come-spilling-out-opinion-column-galant/index.html",
    "pubDate": "Sun, 16 Apr 2023 11:22:36 GMT",
    "source": "cnn"
  },
  {
    "title": "How did Sudan go from casting off despotic rule to this?",
    "link": "https://www.cnn.com/2023/04/17/opinions/sudan-revolution-to-civil-war-lynch/index.html",
    "pubDate": "Mon, 17 Apr 2023 22:45:23 GMT",
    "source": "cnn"
  },
  {
    "title": "Michelle Yeoh set to return in new 'Star Trek' movie",
    "link": "https://www.cnn.com/2023/04/18/entertainment/michelle-yeoh-star-trek-section-31/index.html",
    "pubDate": "Tue, 18 Apr 2023 19:11:23 GMT",
    "source": "cnn"
  },
  {
    "title": "Recap: 'Succession' finds dark humor in the aftershocks",
    "link": "https://www.cnn.com/2023/04/16/entertainment/succession-season-4-episode-4-recap/index.html",
    "pubDate": "Mon, 17 Apr 2023 02:28:12 GMT",
    "source": "cnn"
  },
  {
    "title": "'Yellowjackets' leans hard into '90s music nostalgia, and we're here for it",
    "link": "https://www.cnn.com/2023/04/14/entertainment/yellowjackets-90s-music/index.html",
    "pubDate": "Mon, 01 May 2023 23:02:04 GMT",
    "source": "cnn"
  },
  {
    "title": "Jeremy Renner revisits 'the amazing group of people' who helped him recover from his accident",
    "link": "https://www.cnn.com/2023/04/16/entertainment/jeremy-renner-update/index.html",
    "pubDate": "Sun, 16 Apr 2023 19:04:10 GMT",
    "source": "cnn"
  },
  {
    "title": "Review: 'Barry' takes a whack at its farewell season",
    "link": "https://www.cnn.com/2023/04/14/entertainment/barry-season-4-review/index.html",
    "pubDate": "Fri, 14 Apr 2023 12:33:08 GMT",
    "source": "cnn"
  }
]